[
    {
        "PostId":"73002207",
        "job_score":99
    },
    {
        "PostId":"57192643",
        "job_score":97
    },
    {
        "PostId":"75219974",
        "job_score":94
    },
    {
        "PostId":"75219977",
        "job_score":93
    },
    {
        "PostId":"75219980",
        "job_score":92
    },
    {
        "PostId":"74928503",
        "job_score":92
    },
    {
        "PostId":"75220789",
        "job_score":91
    },
    {
        "PostId":"75422486",
        "job_score":89
    },
    {
        "PostId":"76530004",
        "job_score":89
    },
    {
        "PostId":"74777089",
        "job_score":89
    },
    {
        "PostId":"73382292",
        "job_score":87
    },
    {
        "PostId":"71358671",
        "job_score":86
    },
    {
        "PostId":"75998593",
        "job_score":86
    },
    {
        "PostId":"76494766",
        "job_score":85
    },
    {
        "PostId":"76499389",
        "job_score":81
    },
    {
        "PostId":"74615270",
        "job_score":80
    },
    {
        "PostId":"76062765",
        "job_score":80
    },
    {
        "PostId":"76550767",
        "job_score":80
    },
    {
        "PostId":"75761061",
        "job_score":79
    },
    {
        "PostId":"75080427",
        "job_score":75
    },
    {
        "PostId":"76432656",
        "job_score":75
    },
    {
        "PostId":"73624091",
        "job_score":74
    },
    {
        "PostId":"75265546",
        "job_score":72
    },
    {
        "PostId":"75681159",
        "job_score":72
    },
    {
        "PostId":"76414730",
        "job_score":72
    },
    {
        "PostId":"76347228",
        "job_score":71
    },
    {
        "PostId":"69699264",
        "job_score":71
    },
    {
        "PostId":"74517855",
        "job_score":71
    },
    {
        "PostId":"73866910",
        "job_score":70
    },
    {
        "PostId":"75824572",
        "job_score":70
    },
    {
        "PostId":"76550754",
        "job_score":69
    },
    {
        "PostId":"75750371",
        "job_score":67
    },
    {
        "PostId":"76282615",
        "job_score":65
    },
    {
        "PostId":"73238403",
        "job_score":65
    },
    {
        "PostId":"75760226",
        "job_score":63
    },
    {
        "PostId":"71486532",
        "job_score":63
    },
    {
        "PostId":"74597923",
        "job_score":61
    },
    {
        "PostId":"76538182",
        "job_score":60
    },
    {
        "PostId":"75530171",
        "job_score":60
    },
    {
        "PostId":"76497267",
        "job_score":59
    },
    {
        "PostId":"76251218",
        "job_score":59
    },
    {
        "PostId":"75430381",
        "job_score":57
    },
    {
        "PostId":"76398387",
        "job_score":57
    },
    {
        "PostId":"75380156",
        "job_score":56
    },
    {
        "PostId":"75681775",
        "job_score":56
    },
    {
        "PostId":"76405090",
        "job_score":56
    },
    {
        "PostId":"76399007",
        "job_score":56
    },
    {
        "PostId":"75721884",
        "job_score":55
    },
    {
        "PostId":"76007174",
        "job_score":53
    },
    {
        "PostId":"74955106",
        "job_score":51
    },
    {
        "PostId":"76509968",
        "job_score":48
    },
    {
        "PostId":"76112712",
        "job_score":48
    },
    {
        "PostId":"74550183",
        "job_score":48
    },
    {
        "PostId":"76061645",
        "job_score":48
    },
    {
        "PostId":"74957295",
        "job_score":46
    },
    {
        "PostId":"75533746",
        "job_score":44
    },
    {
        "PostId":"76017888",
        "job_score":44
    },
    {
        "PostId":"76033688",
        "job_score":43
    },
    {
        "PostId":"76448131",
        "job_score":40
    },
    {
        "PostId":"76509546",
        "job_score":39
    },
    {
        "PostId":"76057899",
        "job_score":39
    },
    {
        "PostId":"76104749",
        "job_score":37
    },
    {
        "PostId":"76062734",
        "job_score":37
    },
    {
        "PostId":"76512462",
        "job_score":36
    },
    {
        "PostId":"76241825",
        "job_score":36
    },
    {
        "PostId":"76475675",
        "job_score":36
    },
    {
        "PostId":"73066320",
        "job_score":32
    },
    {
        "PostId":"75948820",
        "job_score":32
    },
    {
        "PostId":"76026961",
        "job_score":31
    },
    {
        "PostId":"76052565",
        "job_score":30
    },
    {
        "PostId":"76535600",
        "job_score":30
    },
    {
        "PostId":"74988257",
        "job_score":30
    },
    {
        "PostId":"76374678",
        "job_score":29
    },
    {
        "PostId":"76222257",
        "job_score":29
    },
    {
        "PostId":"74913754",
        "job_score":29
    },
    {
        "PostId":"76473833",
        "job_score":27
    },
    {
        "PostId":"75948511",
        "job_score":24
    },
    {
        "PostId":"75948796",
        "job_score":21
    },
    {
        "PostId":"76561765",
        "job_score":21
    },
    {
        "PostId":"76192531",
        "job_score":20
    },
    {
        "PostId":"76062424",
        "job_score":19
    },
    {
        "PostId":"76225884",
        "job_score":19
    },
    {
        "PostId":"76430388",
        "job_score":18
    },
    {
        "PostId":"72172733",
        "job_score":17
    },
    {
        "PostId":"72172945",
        "job_score":16
    },
    {
        "PostId":"76152167",
        "job_score":16
    },
    {
        "PostId":"72172793",
        "job_score":16
    },
    {
        "PostId":"76334174",
        "job_score":15
    },
    {
        "PostId":"76437635",
        "job_score":15
    },
    {
        "PostId":"76468993",
        "job_score":14
    },
    {
        "PostId":"76276268",
        "job_score":14
    },
    {
        "PostId":"76473666",
        "job_score":13
    },
    {
        "PostId":"76551256",
        "job_score":11
    },
    {
        "PostId":"75830515",
        "job_score":9
    },
    {
        "PostId":"76495468",
        "job_score":9
    },
    {
        "PostId":"76477930",
        "job_score":9
    },
    {
        "PostId":"76563900",
        "job_score":7
    },
    {
        "PostId":"76017801",
        "job_score":5
    },
    {
        "PostId":"76480181",
        "job_score":4
    },
    {
        "PostId":"76249302",
        "job_score":0
    }
]